{
	"modelTitle":	"G e n e r a l   A l g e b r a i c   M o d e l i n g   S y s t e m",
	"inputSymbols":	{
		"mcoord":	{
			"alias":	"Machine co-coordinates",
			"symtype":	"parameter",
			"headers":	{
				"machines":	{
					"type":	"string",
					"alias":	"machines"
				},
				"x":	{
					"type":	"numeric",
					"alias":	"x"
				},
				"y":	{
					"type":	"numeric",
					"alias":	"y"
				}
			}
		},
		"rscoord":	{
			"alias":	"Recieving and Shipping co-coordinates",
			"symtype":	"parameter",
			"headers":	{
				"rs":	{
					"type":	"string",
					"alias":	"recieving and shipping"
				},
				"x":	{
					"type":	"numeric",
					"alias":	"x"
				},
				"y":	{
					"type":	"numeric",
					"alias":	"y"
				}
			}
		},
		"min_distance":	{
			"alias":	"Minimum distance between different machines",
			"symtype":	"parameter",
			"headers":	{
				"machines":	{
					"type":	"string",
					"alias":	"machines"
				},
				"machines#1":	{
					"type":	"string",
					"alias":	"machines#1"
				},
				"value":	{
					"type":	"numeric",
					"alias":	"Minimum distance between different machines"
				}
			}
		},
		"cm":	{
			"alias":	"Cost of moving machines per distance unit",
			"symtype":	"parameter",
			"headers":	{
				"machines":	{
					"type":	"string",
					"alias":	"machines"
				},
				"value":	{
					"type":	"numeric",
					"alias":	"Cost of moving machines per distance unit"
				}
			}
		},
		"ch":	{
			"alias":	"Cost of moving products per distance unit",
			"symtype":	"parameter",
			"headers":	{
				"products":	{
					"type":	"string",
					"alias":	"products"
				},
				"value":	{
					"type":	"numeric",
					"alias":	"Cost of moving products per distance unit"
				}
			}
		},
		"lowupcoord":	{
			"alias":	"lower and upper bound of the co-coordinats of machines",
			"symtype":	"parameter",
			"headers":	{
				"machines":	{
					"type":	"string",
					"alias":	"machines"
				},
				"xlow":	{
					"type":	"numeric",
					"alias":	"xlow"
				},
				"xup":	{
					"type":	"numeric",
					"alias":	"xup"
				},
				"ylow":	{
					"type":	"numeric",
					"alias":	"ylow"
				},
				"yup":	{
					"type":	"numeric",
					"alias":	"yup"
				}
			}
		}
	},
	"outputSymbols":	{
		"result":	{
			"alias":	"result for old layout",
			"symtype":	"parameter",
			"headers":	{
				"machines":	{
					"type":	"string",
					"alias":	"machines"
				},
				"products":	{
					"type":	"string",
					"alias":	"products"
				},
				"x":	{
					"type":	"numeric",
					"alias":	"x"
				},
				"y":	{
					"type":	"numeric",
					"alias":	"y"
				},
				"newx":	{
					"type":	"numeric",
					"alias":	"newx"
				},
				"newy":	{
					"type":	"numeric",
					"alias":	"newy"
				},
				"ch":	{
					"type":	"numeric",
					"alias":	"ch"
				},
				"cm":	{
					"type":	"numeric",
					"alias":	"cm"
				},
				"xr":	{
					"type":	"numeric",
					"alias":	"xr"
				},
				"yr":	{
					"type":	"numeric",
					"alias":	"yr"
				},
				"xs":	{
					"type":	"numeric",
					"alias":	"xs"
				},
				"ys":	{
					"type":	"numeric",
					"alias":	"ys"
				},
				"status":	{
					"type":	"numeric",
					"alias":	"status"
				}
			}
		},
		"_scalars_out":	{
			"alias":	"Output Scalars",
			"symnames":	["mcost", "poldcost", "pnewcost"],
			"symtext":	["Total cost of moving machines to new location", "Total cost of moving 3 products in old layout", "Total cost of moving 3 products in new layout"],
			"symtypes":	["parameter", "parameter", "parameter"],
			"headers":	{
				"scalar":	{
					"type":	"string",
					"alias":	"Scalar Name"
				},
				"description":	{
					"type":	"string",
					"alias":	"Scalar Description"
				},
				"value":	{
					"type":	"string",
					"alias":	"Scalar Value"
				}
			}
		}
	}
}